a_pandas_ex_tesseract_multirow_regex_fuzz/LICENSE
a_pandas_ex_tesseract_multirow_regex_fuzz/README.MD
a_pandas_ex_tesseract_multirow_regex_fuzz/__init__.py
a_pandas_ex_tesseract_multirow_regex_fuzz/requirements.txt
a_pandas_ex_tesseract_multirow_regex_fuzz/thirdparty.json
a_pandas_ex_tesseract_multirow_regex_fuzz-0.11.dist-info/LICENSE.rst
a_pandas_ex_tesseract_multirow_regex_fuzz-0.11.dist-info/METADATA
a_pandas_ex_tesseract_multirow_regex_fuzz-0.11.dist-info/WHEEL
a_pandas_ex_tesseract_multirow_regex_fuzz-0.11.dist-info/top_level.txt
a_pandas_ex_tesseract_multirow_regex_fuzz-0.11.dist-info/RECORD
