Metadata-Version: 2.1
Name: a_pandas_ex_tesseract_multirow_regex_fuzz
Version: 0.11
Summary: Regex/Fuzz search across multiple rows/Tesseract to pandas.DataFrame
Home-page: https://github.com/hansalemaos/a_pandas_ex_tesseract_multirow_regex_fuzz
Author: Johannes Fischer
Author-email: <aulasparticularesdealemaosp@gmail.com>
License: MIT
Keywords: pandas,series,dataframe,tesseract,fuzz,regex
Classifier: Development Status :: 4 - Beta
Classifier: Programming Language :: Python :: 3 :: Only
Classifier: Programming Language :: Python :: 3.9
Classifier: Topic :: Scientific/Engineering :: Visualization
Classifier: Topic :: Software Development :: Libraries :: Python Modules
Classifier: Topic :: Text Editors :: Text Processing
Classifier: Topic :: Text Processing :: General
Classifier: Topic :: Text Processing :: Indexing
Classifier: Topic :: Text Processing :: Filters
Classifier: Topic :: Utilities
License-File: LICENSE.rst
